LICENSE
README.md
setup.py
py_az_cli.egg-info/PKG-INFO
py_az_cli.egg-info/SOURCES.txt
py_az_cli.egg-info/dependency_links.txt
py_az_cli.egg-info/top_level.txt
pyaz/__init__.py
pyaz/pyaz_utils.py
pyaz/account/__init__.py
pyaz/account/lock/__init__.py
pyaz/account/management_group/__init__.py
pyaz/account/management_group/subscription/__init__.py
pyaz/acr/__init__.py
pyaz/acr/agentpool/__init__.py
pyaz/acr/config/__init__.py
pyaz/acr/config/content_trust/__init__.py
pyaz/acr/config/retention/__init__.py
pyaz/acr/connected_registry/__init__.py
pyaz/acr/connected_registry/install/__init__.py
pyaz/acr/connected_registry/permissions/__init__.py
pyaz/acr/credential/__init__.py
pyaz/acr/encryption/__init__.py
pyaz/acr/helm/__init__.py
pyaz/acr/helm/repo/__init__.py
pyaz/acr/identity/__init__.py
pyaz/acr/network_rule/__init__.py
pyaz/acr/pack/__init__.py
pyaz/acr/private_endpoint_connection/__init__.py
pyaz/acr/private_link_resource/__init__.py
pyaz/acr/replication/__init__.py
pyaz/acr/repository/__init__.py
pyaz/acr/scope_map/__init__.py
pyaz/acr/task/__init__.py
pyaz/acr/task/credential/__init__.py
pyaz/acr/task/identity/__init__.py
pyaz/acr/task/timer/__init__.py
pyaz/acr/taskrun/__init__.py
pyaz/acr/token/__init__.py
pyaz/acr/token/credential/__init__.py
pyaz/acr/webhook/__init__.py
pyaz/acs/__init__.py
pyaz/acs/dcos/__init__.py
pyaz/acs/kubernetes/__init__.py
pyaz/ad/__init__.py
pyaz/ad/app/__init__.py
pyaz/ad/app/credential/__init__.py
pyaz/ad/app/owner/__init__.py
pyaz/ad/app/permission/__init__.py
pyaz/ad/group/__init__.py
pyaz/ad/group/member/__init__.py
pyaz/ad/group/owner/__init__.py
pyaz/ad/signed_in_user/__init__.py
pyaz/ad/sp/__init__.py
pyaz/ad/sp/credential/__init__.py
pyaz/ad/sp/owner/__init__.py
pyaz/ad/user/__init__.py
pyaz/advisor/__init__.py
pyaz/advisor/configuration/__init__.py
pyaz/advisor/recommendation/__init__.py
pyaz/afd/__init__.py
pyaz/afd/custom_domain/__init__.py
pyaz/afd/endpoint/__init__.py
pyaz/afd/log_analytic/__init__.py
pyaz/afd/log_analytic/location/__init__.py
pyaz/afd/log_analytic/metric/__init__.py
pyaz/afd/log_analytic/ranking/__init__.py
