Metadata-Version: 2.1
Name: py-az-cli
Version: 0.1.8
Summary: Pythonic wrapper for az cli
Home-page: https://github.com/py-az-cli/py-az-cli
Author: David P. Moore
Author-email: 9993122+bigdatamoore@users.noreply.github.com
License: MIT
Platform: UNKNOWN
Classifier: License :: OSI Approved :: MIT License
Classifier: Programming Language :: Python :: 3
Classifier: Programming Language :: Python :: 3.9
License-File: LICENSE
